dbqrqa/__init__.py
dbqrqa/builtins.py
dbqrqa/dataset.py
dbqrqa/evaluation.py
dbqrqa/prompts.py
dbqrqa/types.py
dbqrqa/utils.py
dbqrqa/tests/__init__.py
dbqrqa/tests/build_answers.py
dbqrqa/tests/gpt_evaluation.py
dbqrqa/tests/test_dataset.py
dbqrqa/tests/test_evaluation.py
dbqrqa-0.1.1.dist-info/LICENSE
dbqrqa-0.1.1.dist-info/METADATA
dbqrqa-0.1.1.dist-info/WHEEL
dbqrqa-0.1.1.dist-info/top_level.txt
dbqrqa-0.1.1.dist-info/RECORD
