Metadata-Version: 2.1
Name: dbqrqa
Version: 0.1.1
Summary: A Question Answering Dataset on a Hybrid of Database Querying and Reasoning
Home-page: https://dbqr-qa.github.io
Author: Rungsiman Nararatwong
Author-email: Rungsiman Nararatwong <rungsiman@gmail.com>
License: GNU GENERAL PUBLIC LICENSE
Project-URL: Homepage, https://dbqr-qa.github.io
Project-URL: Documentation, https://dbqr-qa.github.io/quickstart.html
Project-URL: Repository, https://github.com/dbqr-qa/dbqr-qa
Project-URL: Issues, https://github.com/dbqr-qa/dbqr-qa/issues
License-File: LICENSE
Requires-Dist: numpy
Requires-Dist: openai ==1.43.1
Requires-Dist: pandas
Requires-Dist: tqdm
